Eliatopia_Library/__init__.py
Eliatopia_Library/elia.py
Eliatopia_Library/example.py
Eliatopia.py-0.1.0.dist-info/LICENSE
Eliatopia.py-0.1.0.dist-info/LICENSE.txt
Eliatopia.py-0.1.0.dist-info/METADATA
Eliatopia.py-0.1.0.dist-info/WHEEL
Eliatopia.py-0.1.0.dist-info/top_level.txt
Eliatopia.py-0.1.0.dist-info/RECORD
