Metadata-Version: 2.1
Name: Eliatopia.py
Version: 0.1.0
Summary: an package that works with Eliatopia\s Api Keys
Home-page: https://github.com/Al3x/Eliatopia_Library
Author: Al3x3y
Author-email: kami.eliatopia@gmail.com
License: UNKNOWN
Project-URL: Bug Tracker, https://github.com/Al3x3y/Eliatopia_Library/issues
Platform: UNKNOWN
Classifier: Programming Language :: Python :: 3
Classifier: License :: OSI Approved :: MIT License
Classifier: Operating System :: OS Independent
Requires-Python: >=3.6
